setup.py
cgroups/__init__.py
cgroups/cgroup.py
cgroups/common.py
cgroups/user.py
cgroups/utils.py
cgroups.egg-info/PKG-INFO
cgroups.egg-info/SOURCES.txt
cgroups.egg-info/dependency_links.txt
cgroups.egg-info/entry_points.txt
cgroups.egg-info/not-zip-safe
cgroups.egg-info/top_level.txt