Metadata-Version: 1.0
Name: cgroups
Version: 0.1.0
Summary: Python module to manage cgroups
Home-page: http://www.xerus-technologies.fr
Author: Francis Bouvier - Cloud Orchestra
Author-email: francis.bouvier@cloudorchestra.io
License: New BSD
Platform: Linux
